Traffic_light/traffic_light_fsm.v
module traffic_light_fsm(
    input clk,
    input rst_n,
    input timer_zero,  // Tín hiệu báo timer đã đếm về 0
    output reg [1:0] current_state,  // Trạng thái hiện tại
    output reg timer_load  // Tín hiệu để load giá trị mới vào timer
);

    // Định nghĩa các trạng thái
    localparam GREEN = 2'b00;
    localparam YELLOW = 2'b01;
    localparam RED = 2'b10;

    reg [1:0] next_state;
    reg pending_state_change; // Cờ delay chuyển trạng thái

    // Xác định trạng thái tiếp theo
    always @(*) begin
        case (current_state)
            GREEN:  next_state = YELLOW;
            YELLOW: next_state = RED;
            RED:    next_state = GREEN;
            default: next_state = GREEN;
        endcase
    end    // Luật chuyển trạng thái và phát xung nạp timer
    always @(posedge clk or negedge rst_n) begin
        if (!rst_n) begin
            current_state <= GREEN;
            timer_load <= 1'b1;
            pending_state_change <= 1'b0;
        end else begin
            if (timer_zero && !pending_state_change) begin
                // Khi timer == 1, chuẩn bị chuyển trạng thái
                current_state <= next_state;
                timer_load <= 1'b1; 
                pending_state_change <= 1'b1;
            end else if (pending_state_change) begin 
                // Clock tiếp theo: tắt load signal
                timer_load <= 1'b0;
                pending_state_change <= 1'b0;
            end else begin
                timer_load <= 1'b0;
            end
        end
    end
endmodule

Traffic_light_fsm/traffic_light_fsm_tb.v
`timescale 1ns / 1ps

module traffic_light_fsm_tb;
    // Parameters
    localparam CLK_PERIOD = 100;  // 100ns clock period (10MHz)
    
    // Signals
    reg clk;
    reg rst_n;
    reg timer_zero;
    wire [1:0] current_state;
    wire timer_load;
    
    // State definitions
    localparam GREEN = 2'b00;
    localparam YELLOW = 2'b01;
    localparam RED = 2'b10;
    
    // String for state display
    reg [8*10-1:0] state_name;
    
    // Instantiate FSM
    traffic_light_fsm uut (
        .clk(clk),
        .rst_n(rst_n),
        .timer_zero(timer_zero),
        .current_state(current_state),
        .timer_load(timer_load)
    );
    
    // Clock generation
    initial begin
        clk = 0;
        forever #(CLK_PERIOD/2) clk = ~clk;
    end
    
    // Convert state to string for display
    always @(*) begin
        case(current_state)
            GREEN:  state_name = "GREEN";
            YELLOW: state_name = "YELLOW";
            RED:    state_name = "RED";
            default: state_name = "UNKNOWN";
        endcase
    end
    
    // Test sequence
    initial begin
        $display("==================================================");
        $display("        TRAFFIC LIGHT FSM TESTBENCH");
        $display("==================================================");
        
        // Create VCD file
        $dumpfile("traffic_light_fsm.vcd");
        $dumpvars(0, traffic_light_fsm_tb);
        
        // Initialize
        rst_n = 0;
        timer_zero = 0;
        
        $display("\n--- PHASE 1: RESET SEQUENCE ---");
        
        // Apply reset
        repeat(3) @(posedge clk);
        $display("Time=%0t | RESET Active | State=%s | timer_load=%b", 
                 $time, state_name, timer_load);
        
        // Release reset
        rst_n = 1;
        @(posedge clk);
        $display("Time=%0t | RESET Released | State=%s | timer_load=%b", 
                 $time, state_name, timer_load);
        
        // Wait for system to stabilize
        repeat(2) @(posedge clk);
        $display("Time=%0t | System Stable | State=%s | timer_load=%b", 
                 $time, state_name, timer_load);
        
        $display("\n--- PHASE 2: GREEN TO YELLOW TRANSITION ---");
        
        // Simulate GREEN phase countdown
        $display("Simulating GREEN phase (15 seconds countdown)...");
        repeat(5) @(posedge clk);  // Normal countdown
        
        // Trigger timer_zero (when timer = 1)
        $display("Time=%0t | Timer about to expire | State=%s | timer_load=%b", 
                 $time, state_name, timer_load);
        
        timer_zero = 1;
        @(posedge clk); // Clock edge where transition happens
        $display("Time=%0t | TRANSITION! | State=%s | timer_load=%b | timer_zero=%b", 
                 $time, state_name, timer_load, timer_zero);
        
        timer_zero = 0;
        @(posedge clk); // Next clock: timer_load should go to 0
        $display("Time=%0t | After Transition | State=%s | timer_load=%b", 
                 $time, state_name, timer_load);
        
        $display("\n--- PHASE 3: YELLOW TO RED TRANSITION ---");
        
        // Simulate YELLOW phase countdown
        repeat(3) @(posedge clk);
        $display("Time=%0t | YELLOW countdown | State=%s | timer_load=%b", 
                 $time, state_name, timer_load);
        
        // Trigger next transition
        timer_zero = 1;
        @(posedge clk);
        $display("Time=%0t | TRANSITION! | State=%s | timer_load=%b | timer_zero=%b", 
                 $time, state_name, timer_load, timer_zero);
        
        timer_zero = 0;
        @(posedge clk);
        $display("Time=%0t | After Transition | State=%s | timer_load=%b", 
                 $time, state_name, timer_load);
        
        $display("\n--- PHASE 4: RED TO GREEN TRANSITION ---");
        
        // Simulate RED phase countdown
        repeat(5) @(posedge clk);
        $display("Time=%0t | RED countdown | State=%s | timer_load=%b", 
                 $time, state_name, timer_load);
        
        // Trigger next transition
        timer_zero = 1;
        @(posedge clk);
        $display("Time=%0t | TRANSITION! | State=%s | timer_load=%b | timer_zero=%b", 
                 $time, state_name, timer_load, timer_zero);
        
        timer_zero = 0;
        @(posedge clk);
        $display("Time=%0t | After Transition | State=%s | timer_load=%b", 
                 $time, state_name, timer_load);
        
        $display("\n--- PHASE 5: VERIFY FULL CYCLE ---");
        
        // One more transition to verify cycle
        repeat(3) @(posedge clk);
        timer_zero = 1;
        @(posedge clk);
        $display("Time=%0t | FULL CYCLE DONE | State=%s | timer_load=%b", 
                 $time, state_name, timer_load);
        
        timer_zero = 0;
        @(posedge clk);
        
        $display("\n==================================================");
        $display("            SIMULATION COMPLETED");
        $display("==================================================");
        $display("Verified: GREEN -> YELLOW -> RED -> GREEN cycle");
        $display("timer_load pulse behavior: OK");
        $display("State transitions: OK");
        
        repeat(5) @(posedge clk);
        $finish;
    end
    
    // Detailed monitor
    initial begin
        $monitor("Time=%0t | CLK=%b | RST=%b | timer_zero=%b | State=%-7s | timer_load=%b | pending=%b", 
                 $time, clk, rst_n, timer_zero, state_name, timer_load, uut.pending_state_change);
    end

endmodule

Traffic_light_fsm/traffic_light_fsm.vcd
$date
	Mon Jun 16 23:00:44 2025
$end
$version
	Icarus Verilog
$end
$timescale
	1ps
$end
$scope module traffic_light_fsm_tb $end
$var wire 1 ! timer_load $end
$var wire 2 " current_state [1:0] $end
$var parameter 32 # CLK_PERIOD $end
$var parameter 2 $ GREEN $end
$var parameter 2 % RED $end
$var parameter 2 & YELLOW $end
$var reg 1 ' clk $end
$var reg 1 ( rst_n $end
$var reg 80 ) state_name [79:0] $end
$var reg 1 * timer_zero $end
$scope module uut $end
$var wire 1 ' clk $end
$var wire 1 ( rst_n $end
$var wire 1 * timer_zero $end
$var parameter 2 + GREEN $end
$var parameter 2 , RED $end
$var parameter 2 - YELLOW $end
$var reg 2 . current_state [1:0] $end
$var reg 2 / next_state [1:0] $end
$var reg 1 0 pending_state_change $end
$var reg 1 ! timer_load $end
$upscope $end
$upscope $end
$enddefinitions $end
$comment Show the parameter values. $end
$dumpall
b1 -
b10 ,
b0 +
b1 &
b10 %
b0 $
b1100100 #
$end
#0
$dumpvars
00
b1 /
b0 .
0*
b100011101010010010001010100010101001110 )
0(
0'
b0 "
1!
$end
#50000
1'
#100000
0'
#150000
1'
#200000
0'
#250000
0!
1(
1'
#300000
0'
#350000
1'
#400000
0'
#450000
1'
#500000
0'
#550000
1'
#600000
0'
#650000
1'
#700000
0'
#750000
1'
#800000
0'
#850000
1'
#900000
0'
#950000
1'
#1000000
0'
#1050000
b10 /
b10110010100010101001100010011000100111101010111 )
10
1!
b1 "
b1 .
1*
1'
#1100000
0'
#1150000
00
0!
0*
1'
#1200000
0'
#1250000
1'
#1300000
0'
#1350000
1'
#1400000
0'
#1450000
1'
#1500000
0'
#1550000
b10100100100010101000100 )
b0 /
10
1!
b10 "
b10 .
1*
1'
#1600000
0'
#1650000
00
0!
0*
1'
#1700000
0'
#1750000
1'
#1800000
0'
#1850000
1'
#1900000
0'
#1950000
1'
#2000000
0'
#2050000
1'
#2100000
0'
#2150000
1'
#2200000
0'
#2250000
b1 /
b100011101010010010001010100010101001110 )
10
1!
b0 "
b0 .
1*
1'
#2300000
0'
#2350000
00
0!
0*
1'
#2400000
0'
#2450000
1'
#2500000
0'
#2550000
1'
#2600000
0'
#2650000
1'
#2700000
0'
#2750000
b10110010100010101001100010011000100111101010111 )
b10 /
10
1!
b1 "
b1 .
1*
1'
#2800000
0'
#2850000
00
0!
0*
1'
